inorbit/__init__.py
inorbit/cli.py
inorbit/client.py
inorbit/constants.py
inorbit/exceptions.py
tests/__init__.py
tests/test_client.py
tests/test_robots_cli.py
inorbit_cli-0.16.0.dist-info/LICENSE
inorbit_cli-0.16.0.dist-info/METADATA
inorbit_cli-0.16.0.dist-info/WHEEL
inorbit_cli-0.16.0.dist-info/entry_points.txt
inorbit_cli-0.16.0.dist-info/top_level.txt
inorbit_cli-0.16.0.dist-info/RECORD
