Metadata-Version: 2.1
Name: inorbit-cli
Version: 0.16.0
Summary: CLI tool to interact with InOrbit Cloud Platform
Author: InOrbit Inc.
Author-email: support@inorbit.ai
License: Proprietary
Classifier: Programming Language :: Python :: 3.8
Classifier: Operating System :: OS Independent
Classifier: License :: Other/Proprietary License
Requires-Python: >=3.7
License-File: LICENSE
Requires-Dist: click >=8.0.3
Requires-Dist: tabulate >=0.8.9
Requires-Dist: requests >=2.26.0
Requires-Dist: pyyaml >=5.3.0
Provides-Extra: dev
Requires-Dist: twine ; extra == 'dev'
Requires-Dist: lark ; extra == 'dev'
Requires-Dist: pytest ; extra == 'dev'
Requires-Dist: pytest-env ; extra == 'dev'
Requires-Dist: requests-mock ; extra == 'dev'
Requires-Dist: black ; extra == 'dev'
